odoo/addons/purchase_order_shipping_date/README.rst
odoo/addons/purchase_order_shipping_date/__init__.py
odoo/addons/purchase_order_shipping_date/__manifest__.py
odoo/addons/purchase_order_shipping_date/i18n/it.po
odoo/addons/purchase_order_shipping_date/i18n/purchase_order_shipping_date.pot
odoo/addons/purchase_order_shipping_date/models/__init__.py
odoo/addons/purchase_order_shipping_date/models/purchase_order.py
odoo/addons/purchase_order_shipping_date/readme/CONTRIBUTORS.rst
odoo/addons/purchase_order_shipping_date/readme/DESCRIPTION.rst
odoo/addons/purchase_order_shipping_date/reports/report_purchase_order.xml
odoo/addons/purchase_order_shipping_date/static/description/icon.png
odoo/addons/purchase_order_shipping_date/static/description/index.html
odoo/addons/purchase_order_shipping_date/views/purchase_order.xml
odoo14_addon_purchase_order_shipping_date-14.0.1.0.1.dist-info/METADATA
odoo14_addon_purchase_order_shipping_date-14.0.1.0.1.dist-info/WHEEL
odoo14_addon_purchase_order_shipping_date-14.0.1.0.1.dist-info/top_level.txt
odoo14_addon_purchase_order_shipping_date-14.0.1.0.1.dist-info/RECORD
